cabbage/__init__.py
cabbage/amqp.py
cabbage/test_utils.py
cabbage/utils.py
cabbage-1.0.0.dist-info/AUTHORS.md
cabbage-1.0.0.dist-info/METADATA
cabbage-1.0.0.dist-info/WHEEL
cabbage-1.0.0.dist-info/top_level.txt
cabbage-1.0.0.dist-info/zip-safe
cabbage-1.0.0.dist-info/RECORD
